argparse_gen/__init__.py
argparse_gen/argparse_gen.py
argparse_gen/main.py
argparse_gen/param_def.py
argparse_gen/py.typed
argparse_gen/utils.py
argparse_gen/version.py
argparse_gen-1.0.1.dist-info/METADATA
argparse_gen-1.0.1.dist-info/WHEEL
argparse_gen-1.0.1.dist-info/entry_points.txt
argparse_gen-1.0.1.dist-info/RECORD
