Metadata-Version: 2.1
Name: argparse_gen
Version: 1.0.1
Summary: Argparse code generator.
Project-URL: Homepage, https://github.com/vsego/argparse_gen
Project-URL: Bug Tracker, https://github.com/vsego/argparse_gen/issues
Project-URL: Changelog, https://github.com/vsego/argparse_gen/blob/master/CHANGELOG.md
Author-email: Vedran Sego <vsego@vsego.org>
License-Expression: MIT
Classifier: Operating System :: OS Independent
Classifier: Programming Language :: Python :: 3.10
Classifier: Programming Language :: Python :: 3.11
Classifier: Typing :: Typed
Requires-Python: >=3.10
